kraken_cache/kraken_cache.py
kraken_cache-0.0.3.dist-info/LICENSE.txt
kraken_cache-0.0.3.dist-info/METADATA
kraken_cache-0.0.3.dist-info/WHEEL
kraken_cache-0.0.3.dist-info/top_level.txt
kraken_cache-0.0.3.dist-info/RECORD
